EXASOL/__init__.py
EXASOL/test.py
EXASOL_DB_API-6.0.0.dist-info/METADATA
EXASOL_DB_API-6.0.0.dist-info/RECORD
EXASOL_DB_API-6.0.0.dist-info/WHEEL
EXASOL_DB_API-6.0.0.dist-info/top_level.txt
